dbpost2/__init__.py
dbpost2/client.py
dbpost2/constants.py
dbpost2/crypto_helper.py
dbpost2/log.py
dbpost2/server.py
dbpost2/utils.py
dbpost2-0.3.2.dist-info/METADATA
dbpost2-0.3.2.dist-info/RECORD
dbpost2-0.3.2.dist-info/WHEEL
dbpost2-0.3.2.dist-info/top_level.txt
