Metadata-Version: 2.1
Name: dbpost2
Version: 0.3.2
Summary: proxy for save db data. support mysql、sqlite、mongodb
Home-page: https://github.com/dantezhu/dbpost
Author: grey
Author-email: greyeee@gmail.com
License: BSD
Platform: UNKNOWN
Requires-Dist: pymongo
Requires-Dist: dataset
